txttree/__init__.py
txttree/__main__.py
txttree/app.py
txttree-0.0.1.dist-info/LICENSE
txttree-0.0.1.dist-info/METADATA
txttree-0.0.1.dist-info/WHEEL
txttree-0.0.1.dist-info/top_level.txt
txttree-0.0.1.dist-info/RECORD
