Metadata-Version: 2.2
Name: txttree
Version: 0.0.1
Summary: Command line tool for organizing and displaying hierarchical relationships using a folder-based structure and text files.
Home-page: https://github.com/spmvg/txttree
Author: Steven van Gemert
Author-email: steven@vangemert.dev
License: MIT
Classifier: Development Status :: 4 - Beta
Classifier: License :: OSI Approved :: MIT License
Classifier: Programming Language :: Python :: 3
Requires-Python: >=3.10
License-File: LICENSE
Requires-Dist: typer
